dmt/core.py
data_migration_tool-0.1.dist-info/METADATA
data_migration_tool-0.1.dist-info/WHEEL
data_migration_tool-0.1.dist-info/entry_points.txt
data_migration_tool-0.1.dist-info/top_level.txt
data_migration_tool-0.1.dist-info/RECORD
