Metadata-Version: 2.1
Name: data_migration_tool
Version: 0.1
Summary: A data migration tool (GCP, BigQuery)
Author-email: Jean-Baptiste Braun <jbaptiste.braun@gmail.com>
License: MIT License
Project-URL: homepage, https://github.com/jbbqqf/data_migration_tool
Classifier: Programming Language :: Python :: 3
Classifier: License :: OSI Approved :: MIT License
Classifier: Operating System :: OS Independent
Requires-Python: >=3.6
Requires-Dist: google-cloud-bigquery==3.25.0
